de/core.py
de_core-0.2.24.dist-info/LICENSE.md
de_core-0.2.24.dist-info/METADATA
de_core-0.2.24.dist-info/WHEEL
de_core-0.2.24.dist-info/top_level.txt
de_core-0.2.24.dist-info/RECORD
